Workbook

Sheet Dashboard
A1: CONTROLE FINANCEIRO PREMIUM • TELEGRAM
A2: Painel principal com orçamento mensal, contas, metas e acompanhamento em tempo real.
A4: Mês =Resumo_Mensal!B3 | C4: Renda líquida base =Config!B6 | E4: Gasto do mês =Resumo_Mensal!C17 | G4: Saldo do orçamento =Resumo_Mensal!D17
A8: Categoria | B8: Limite | C8: Gasto | D8: Saldo | E8: % Uso | F8: Status | G8: Prioridade | H8: Observação
A9: =Resumo_Mensal!A6 | B9: =Resumo_Mensal!B6 | C9: =Resumo_Mensal!C6 | D9: =Resumo_Mensal!D6 | E9: =Resumo_Mensal!E6 | F9: =Resumo_Mensal!F6 | G9: =XLOOKUP(A9,Limites!A4:A13,Limites!E4:E13,"") | H9: =XLOOKUP(A9,Limites!A4:A13,Limites!D4:D13,"")
A10: =Resumo_Mensal!A7 | B10: =Resumo_Mensal!B7 | C10: =Resumo_Mensal!C7 | D10: =Resumo_Mensal!D7 | E10: =Resumo_Mensal!E7 | F10: =Resumo_Mensal!F7 | G10: =XLOOKUP(A10,Limites!A4:A13,Limites!E4:E13,"") | H10: =XLOOKUP(A10,Limites!A4:A13,Limites!D4:D13,"")
A11: =Resumo_Mensal!A8 | B11: =Resumo_Mensal!B8 | C11: =Resumo_Mensal!C8 | D11: =Resumo_Mensal!D8 | E11: =Resumo_Mensal!E8 | F11: =Resumo_Mensal!F8 | G11: =XLOOKUP(A11,Limites!A4:A13,Limites!E4:E13,"") | H11: =XLOOKUP(A11,Limites!A4:A13,Limites!D4:D13,"")
A12: =Resumo_Mensal!A9 | B12: =Resumo_Mensal!B9 | C12: =Resumo_Mensal!C9 | D12: =Resumo_Mensal!D9 | E12: =Resumo_Mensal!E9 | F12: =Resumo_Mensal!F9 | G12: =XLOOKUP(A12,Limites!A4:A13,Limites!E4:E13,"") | H12: =XLOOKUP(A12,Limites!A4:A13,Limites!D4:D13,"")
A13: =Resumo_Mensal!A10 | B13: =Resumo_Mensal!B10 | C13: =Resumo_Mensal!C10 | D13: =Resumo_Mensal!D10 | E13: =Resumo_Mensal!E10 | F13: =Resumo_Mensal!F10 | G13: =XLOOKUP(A13,Limites!A4:A13,Limites!E4:E13,"") | H13: =XLOOKUP(A13,Limites!A4:A13,Limites!D4:D13,"")
A14: =Resumo_Mensal!A11 | B14: =Resumo_Mensal!B11 | C14: =Resumo_Mensal!C11 | D14: =Resumo_Mensal!D11 | E14: =Resumo_Mensal!E11 | F14: =Resumo_Mensal!F11 | G14: =XLOOKUP(A14,Limites!A4:A13,Limites!E4:E13,"") | H14: =XLOOKUP(A14,Limites!A4:A13,Limites!D4:D13,"")
A15: =Resumo_Mensal!A12 | B15: =Resumo_Mensal!B12 | C15: =Resumo_Mensal!C12 | D15: =Resumo_Mensal!D12 | E15: =Resumo_Mensal!E12 | F15: =Resumo_Mensal!F12 | G15: =XLOOKUP(A15,Limites!A4:A13,Limites!E4:E13,"") | H15: =XLOOKUP(A15,Limites!A4:A13,Limites!D4:D13,"")
A16: =Resumo_Mensal!A13 | B16: =Resumo_Mensal!B13 | C16: =Resumo_Mensal!C13 | D16: =Resumo_Mensal!D13 | E16: =Resumo_Mensal!E13 | F16: =Resumo_Mensal!F13 | G16: =XLOOKUP(A16,Limites!A4:A13,Limites!E4:E13,"") | H16: =XLOOKUP(A16,Limites!A4:A13,Limites!D4:D13,"")
A17: =Resumo_Mensal!A14 | B17: =Resumo_Mensal!B14 | C17: =Resumo_Mensal!C14 | D17: =Resumo_Mensal!D14 | E17: =Resumo_Mensal!E14 | F17: =Resumo_Mensal!F14 | G17: =XLOOKUP(A17,Limites!A4:A13,Limites!E4:E13,"") | H17: =XLOOKUP(A17,Limites!A4:A13,Limites!D4:D13,"")
A18: =Resumo_Mensal!A15 | B18: =Resumo_Mensal!B15 | C18: =Resumo_Mensal!C15 | D18: =Resumo_Mensal!D15 | E18: =Resumo_Mensal!E15 | F18: =Resumo_Mensal!F15 | G18: =XLOOKUP(A18,Limites!A4:A13,Limites!E4:E13,"") | H18: =XLOOKUP(A18,Limites!A4:A13,Limites!D4:D13,"")
A21: Atalhos do Telegram
A22: /gasto gasolina 120 shell | D22: Lança um gasto e responde com saldo da categoria
A23: /status | D23: Mostra o painel do mês
A24: /status carro | D24: Mostra só a categoria desejada
A25: /contas | D25: Lista contas próximas do vencimento
A26: /pagar internet e celular | D26: Marca a conta como paga
A27: gasolina 80 | D27: Também aceita mensagem simples sem barra

Sheet Limites
A1: ORÇAMENTO MENSAL BASE
A3: Categoria | B3: Limite Mensal | C3: Tipo | D3: Observação | E3: Prioridade
A4: Moradia | B4: 1700 | C4: Fixo | D4: Prestação da casa | E4: Essencial
A5: Carro | B5: 1400 | C5: Fixo | D5: Prestação do carro | E5: Essencial
A6: Internet e Celular | B6: 212 | C6: Fixo | D6: Plano mensal de conectividade | E6: Essencial
A7: Luz e Streaming | B7: 150 | C7: Fixo | D7: Energia + plataformas | E7: Essencial
A8: Pet | B8: 93.33 | C8: Provisão | D8: Ração trimestral rateada por mês | E8: Essencial
A9: Combustível | B9: 350 | C9: Variável | D9: Deslocamentos do mês | E9: Importante
A10: Lazer | B10: 150 | C10: Variável | D10: Saídas e pequenas compras | E10: Controlável
A11: Saúde e Farmácia | B11: 100 | C11: Variável | D11: Remédios e emergências leves | E11: Importante
A12: Imprevistos | B12: 144.67 | C12: Variável | D12: Margem para ajustes do mês | E12: Importante
A13: Reserva de Emergência | B13: 1000 | C13: Meta | D13: Transferir para reserva mensal | E13: Estratégico
A15: Total planejado | B15: =SUM(B4:B13)

Sheet Contas_Fixas
A1: CONTAS FIXAS E COBRANÇAS
A3: Conta | B3: Categoria | C3: Valor | D3: Frequência | E3: Dia Venc. | F3: Tipo | G3: Ativa? | H3: Observação
A4: Casa | B4: Moradia | C4: 1700 | D4: Mensal | E4: 5 | F4: Obrigatória | G4: Sim | H4: Ajuste o vencimento real se necessário.
A5: Carro | B5: Carro | C5: 1400 | D5: Mensal | E5: 10 | F5: Obrigatória | G5: Sim | H5: 57 parcelas restantes.
A6: Internet + Celular | B6: Internet e Celular | C6: 212 | D6: Mensal | E6: 12 | F6: Obrigatória | G6: Sim | H6: Conta conjunta de conectividade.
A7: Luz + Streaming | B7: Luz e Streaming | C7: 150 | D7: Mensal | E7: 20 | F7: Obrigatória | G7: Sim | H7: Pode separar em duas contas se quiser.
A8: Ração Cachorrinha | B8: Pet | C8: 280 | D8: Trimestral | E8: 25 | F8: Obrigatória | G8: Sim | H8: Compra a cada 3 meses.

Sheet Lancamentos
A1: LANÇAMENTOS • TELEGRAM + WEB
A3: Data | B3: Mês | C3: Categoria | D3: Subcategoria | E3: Tipo | F3: Descrição | G3: Valor | H3: Canal | I3: Status | J3: Observação
A4: 46117 | B4: =TEXT(A4,"yyyy-mm") | C4: Moradia | D4: Parcela | E4: gasto | F4: Prestação da casa | G4: 1700 | H4: sistema | I4: Pago | J4: Lançamento inicial
A5: 46122 | B5: =TEXT(A5,"yyyy-mm") | C5: Carro | D5: Parcela | E5: gasto | F5: Prestação do carro | G5: 1400 | H5: sistema | I5: Pago | J5: Lançamento inicial
A6: 46124 | B6: =TEXT(A6,"yyyy-mm") | C6: Internet e Celular | D6: Plano | E6: gasto | F6: Internet e celular | G6: 212 | H6: sistema | I6: Pago | J6: Lançamento inicial
A7: 46132 | B7: =TEXT(A7,"yyyy-mm") | C7: Luz e Streaming | D7: Mensal | E7: gasto | F7: Energia e plataformas | G7: 150 | H7: sistema | I7: Pago | J7: Lançamento inicial
A8: 46129 | B8: 2026-04 | C8: Combustível | E8: gasto | F8: shell | G8: 120 | H8: telegram | I8: Pago
B9: =IF(A9="","",TEXT(A9,"yyyy-mm"))
B10: =IF(A10="","",TEXT(A10,"yyyy-mm"))
B11: =IF(A11="","",TEXT(A11,"yyyy-mm"))
B12: =IF(A12="","",TEXT(A12,"yyyy-mm"))
B13: =IF(A13="","",TEXT(A13,"yyyy-mm"))
B14: =IF(A14="","",TEXT(A14,"yyyy-mm"))
B15: =IF(A15="","",TEXT(A15,"yyyy-mm"))
B16: =IF(A16="","",TEXT(A16,"yyyy-mm"))
B17: =IF(A17="","",TEXT(A17,"yyyy-mm"))
B18: =IF(A18="","",TEXT(A18,"yyyy-mm"))
B19: =IF(A19="","",TEXT(A19,"yyyy-mm"))
B20: =IF(A20="","",TEXT(A20,"yyyy-mm"))
... B304: =IF(A304="","",TEXT(A304,"yyyy-mm"))

Sheet Resumo_Mensal
A1: RESUMO MENSAL E LIMITES
A3: Mês analisado | B3: 2026-04 | D3: Renda líquida base | E3: =Config!B6 | F3: Benefício alimentação | G3: =Config!B7
A5: Categoria | B5: Limite | C5: Gasto do Mês | D5: Saldo | E5: % Consumido | F5: Status | G5: Tipo
A6: Moradia | B6: =XLOOKUP(A6,Limites!A4:A13,Limites!B4:B13,0) | C6: =SUMIFS(Lancamentos!$G$4:$G$304,Lancamentos!$C$4:$C$304,$A6,Lancamentos!$B$4:$B$304,$B$3,Lancamentos!$E$4:$E$304,"gasto") | D6: =B6-C6 | E6: =IFERROR(C6/B6,0) | F6: =IF(C6>B6,"ESTOURADO",IF(C6>=B6*0.85,"ALERTA","OK")) | G6: =XLOOKUP(A6,Limites!A4:A13,Limites!C4:C13,"")
A7: Carro | B7: =XLOOKUP(A7,Limites!A4:A13,Limites!B4:B13,0) | C7: =SUMIFS(Lancamentos!$G$4:$G$304,Lancamentos!$C$4:$C$304,$A7,Lancamentos!$B$4:$B$304,$B$3,Lancamentos!$E$4:$E$304,"gasto") | D7: =B7-C7 | E7: =IFERROR(C7/B7,0) | F7: =IF(C7>B7,"ESTOURADO",IF(C7>=B7*0.85,"ALERTA","OK")) | G7: =XLOOKUP(A7,Limites!A4:A13,Limites!C4:C13,"")
A8: Internet e Celular | B8: =XLOOKUP(A8,Limites!A4:A13,Limites!B4:B13,0) | C8: =SUMIFS(Lancamentos!$G$4:$G$304,Lancamentos!$C$4:$C$304,$A8,Lancamentos!$B$4:$B$304,$B$3,Lancamentos!$E$4:$E$304,"gasto") | D8: =B8-C8 | E8: =IFERROR(C8/B8,0) | F8: =IF(C8>B8,"ESTOURADO",IF(C8>=B8*0.85,"ALERTA","OK")) | G8: =XLOOKUP(A8,Limites!A4:A13,Limites!C4:C13,"")
A9: Luz e Streaming | B9: =XLOOKUP(A9,Limites!A4:A13,Limites!B4:B13,0) | C9: =SUMIFS(Lancamentos!$G$4:$G$304,Lancamentos!$C$4:$C$304,$A9,Lancamentos!$B$4:$B$304,$B$3,Lancamentos!$E$4:$E$304,"gasto") | D9: =B9-C9 | E9: =IFERROR(C9/B9,0) | F9: =IF(C9>B9,"ESTOURADO",IF(C9>=B9*0.85,"ALERTA","OK")) | G9: =XLOOKUP(A9,Limites!A4:A13,Limites!C4:C13,"")
A10: Pet | B10: =XLOOKUP(A10,Limites!A4:A13,Limites!B4:B13,0) | C10: =SUMIFS(Lancamentos!$G$4:$G$304,Lancamentos!$C$4:$C$304,$A10,Lancamentos!$B$4:$B$304,$B$3,Lancamentos!$E$4:$E$304,"gasto") | D10: =B10-C10 | E10: =IFERROR(C10/B10,0) | F10: =IF(C10>B10,"ESTOURADO",IF(C10>=B10*0.85,"ALERTA","OK")) | G10: =XLOOKUP(A10,Limites!A4:A13,Limites!C4:C13,"")
A11: Combustível | B11: =XLOOKUP(A11,Limites!A4:A13,Limites!B4:B13,0) | C11: =SUMIFS(Lancamentos!$G$4:$G$304,Lancamentos!$C$4:$C$304,$A11,Lancamentos!$B$4:$B$304,$B$3,Lancamentos!$E$4:$E$304,"gasto") | D11: =B11-C11 | E11: =IFERROR(C11/B11,0) | F11: =IF(C11>B11,"ESTOURADO",IF(C11>=B11*0.85,"ALERTA","OK")) | G11: =XLOOKUP(A11,Limites!A4:A13,Limites!C4:C13,"")
A12: Lazer | B12: =XLOOKUP(A12,Limites!A4:A13,Limites!B4:B13,0) | C12: =SUMIFS(Lancamentos!$G$4:$G$304,Lancamentos!$C$4:$C$304,$A12,Lancamentos!$B$4:$B$304,$B$3,Lancamentos!$E$4:$E$304,"gasto") | D12: =B12-C12 | E12: =IFERROR(C12/B12,0) | F12: =IF(C12>B12,"ESTOURADO",IF(C12>=B12*0.85,"ALERTA","OK")) | G12: =XLOOKUP(A12,Limites!A4:A13,Limites!C4:C13,"")
A13: Saúde e Farmácia | B13: =XLOOKUP(A13,Limites!A4:A13,Limites!B4:B13,0) | C13: =SUMIFS(Lancamentos!$G$4:$G$304,Lancamentos!$C$4:$C$304,$A13,Lancamentos!$B$4:$B$304,$B$3,Lancamentos!$E$4:$E$304,"gasto") | D13: =B13-C13 | E13: =IFERROR(C13/B13,0) | F13: =IF(C13>B13,"ESTOURADO",IF(C13>=B13*0.85,"ALERTA","OK")) | G13: =XLOOKUP(A13,Limites!A4:A13,Limites!C4:C13,"")
A14: Imprevistos | B14: =XLOOKUP(A14,Limites!A4:A13,Limites!B4:B13,0) | C14: =SUMIFS(Lancamentos!$G$4:$G$304,Lancamentos!$C$4:$C$304,$A14,Lancamentos!$B$4:$B$304,$B$3,Lancamentos!$E$4:$E$304,"gasto") | D14: =B14-C14 | E14: =IFERROR(C14/B14,0) | F14: =IF(C14>B14,"ESTOURADO",IF(C14>=B14*0.85,"ALERTA","OK")) | G14: =XLOOKUP(A14,Limites!A4:A13,Limites!C4:C13,"")
A15: Reserva de Emergência | B15: =XLOOKUP(A15,Limites!A4:A13,Limites!B4:B13,0) | C15: =SUMIFS(Lancamentos!$G$4:$G$304,Lancamentos!$C$4:$C$304,$A15,Lancamentos!$B$4:$B$304,$B$3,Lancamentos!$E$4:$E$304,"gasto") | D15: =B15-C15 | E15: =IFERROR(C15/B15,0) | F15: =IF(C15>B15,"ESTOURADO",IF(C15>=B15*0.85,"ALERTA","OK")) | G15: =XLOOKUP(A15,Limites!A4:A13,Limites!C4:C13,"")
A17: Total do orçamento | B17: =SUM(B6:B15) | C17: =SUM(C6:C15) | D17: =SUM(D6:D15) | E17: =IFERROR(C17/B17,0) | F17: =IF(C17>B17,"ESTOURADO",IF(C17>=B17*0.85,"ALERTA","OK"))
A20: Receitas lançadas no mês | B20: =SUMIFS(Lancamentos!$G$4:$G$304,Lancamentos!$B$4:$B$304,$B$3,Lancamentos!$E$4:$E$304,"receita") | D20: Caixa projetado | E20: =E3+B20-C17

Sheet Fluxo_Caixa
A1: FLUXO DE CAIXA MENSAL
A3: Item | B3: Valor | C3: Tipo | D3: Origem | E3: Observação | F3: Status
A4: Renda líquida do casal | B4: 5300 | C4: Entrada | D4: Config | E4: Base usada no planejamento | F4: Ativo
A5: Benefício alimentação | B5: 1400 | C5: Benefício | D5: Config | E5: Não entra como caixa, mas alivia o mercado | F5: Ativo
A6: Total orçamento planejado | B6: =Resumo_Mensal!B17 | C6: Saída | D6: Resumo | E6: Soma dos limites mensais | F6: Ativo
A7: Gasto lançado no mês | B7: =Resumo_Mensal!C17 | C7: Saída | D7: Resumo | E7: Valores já registrados | F7: Dinâmico
A8: Saldo ainda disponível | B8: =Resumo_Mensal!D17 | C8: Saldo | D8: Resumo | E8: Quanto ainda cabe no orçamento | F8: Dinâmico

Sheet Planejamento
A1: PLANO ESTRATÉGICO RECOMENDADO
A3: Item | B3: Valor | C3: Observação
A4: Renda líquida estimada do casal | B4: 5300 | C4: Base do orçamento
A5: Benefício alimentação | B5: 1400 | C5: Ajuda a segurar mercado e refeições
A6: Meta da reserva de emergência | B6: 12000 | C6: Meta mínima sugerida
A7: Aporte mensal ideal para reserva | B7: 1000 | C7: Prioridade até completar a meta
A8: Parcela do carro | B8: 1400 | C8: Maior peso além da moradia
A9: Parcelas restantes do carro | B9: 57 | C9: Avaliar amortização após reserva
A10: Parcela da casa | B10: 1700 | C10: Não priorizar quitação agora
A11: Parcelas restantes da casa | B11: 420 | C11: Longo prazo

Sheet Comandos_Telegram
A1: COMANDOS DO TELEGRAM
A3: Comando | B3: Exemplo | C3: Resposta esperada
A4: Lançar gasto | B4: /gasto gasolina 120 shell | C4: Lança em Combustível e devolve saldo da categoria
A5: Mensagem simples | B5: gasolina 120 | C5: Lança gasto com sintaxe curta
A6: Lançar receita | B6: /receita extra 500 freela | C6: Registra entrada extraordinária
A7: Ver status geral | B7: /status | C7: Mostra gasto total, saldo e alertas
A8: Ver categoria | B8: /status carro | C8: Mostra gasto e saldo do orçamento da categoria
A9: Limites | B9: /limites | C9: Lista todas as categorias com limite e saldo
A10: Contas próximas | B10: /contas | C10: Lista vencimentos próximos
A11: Marcar conta paga | B11: /pagar internet e celular | C11: Registra a conta como paga
A12: Ajuda | B12: /ajuda | C12: Mostra o menu do bot

Sheet Config
A1: CONFIGURAÇÕES BASE
A3: Chave | B3: Valor | C3: Observação
A4: nome_projeto | B4: Financeiro Telegram Premium | C4: Nome do sistema
A5: moeda | B5: BRL | C5: Padrão monetário
A6: renda_liquida_base | B6: 5300 | C6: Estimativa mensal do casal
A7: beneficio_alimentacao | B7: 1400 | C7: Não entra como caixa do mês
A8: dias_alerta_contas | B8: 5 | C8: Antecedência dos avisos
A9: chat_id_padrao | C9: Preencher após descobrir o chat do Telegram
A10: bot_nome | B10: Seu Controle Financeiro | C10: Texto livre
